odoo/addons/delivery_roulier/README.rst
odoo/addons/delivery_roulier/__init__.py
odoo/addons/delivery_roulier/__manifest__.py
odoo/addons/delivery_roulier/decorator.py
odoo/addons/delivery_roulier/demo/product.xml
odoo/addons/delivery_roulier/i18n/delivery_roulier.pot
odoo/addons/delivery_roulier/i18n/es.po
odoo/addons/delivery_roulier/i18n/it.po
odoo/addons/delivery_roulier/models/__init__.py
odoo/addons/delivery_roulier/models/delivery_carrier.py
odoo/addons/delivery_roulier/models/stock_move_line.py
odoo/addons/delivery_roulier/models/stock_picking.py
odoo/addons/delivery_roulier/models/stock_quant_package.py
odoo/addons/delivery_roulier/readme/CONFIGURE.md
odoo/addons/delivery_roulier/readme/CONTRIBUTORS.md
odoo/addons/delivery_roulier/readme/DESCRIPTION.md
odoo/addons/delivery_roulier/readme/USAGE.md
odoo/addons/delivery_roulier/static/description/icon.png
odoo/addons/delivery_roulier/static/description/index.html
odoo/addons/delivery_roulier/tests/__init__.py
odoo/addons/delivery_roulier/tests/models.py
odoo/addons/delivery_roulier/tests/test_delivery_roulier.py
odoo/addons/delivery_roulier/views/stock_quant_package.xml
odoo_addon_delivery_roulier-18.0.1.0.0.2.dist-info/METADATA
odoo_addon_delivery_roulier-18.0.1.0.0.2.dist-info/WHEEL
odoo_addon_delivery_roulier-18.0.1.0.0.2.dist-info/top_level.txt
odoo_addon_delivery_roulier-18.0.1.0.0.2.dist-info/RECORD
