Metadata-Version: 2.1
Name: odoo-addon-delivery_roulier
Version: 18.0.1.0.0.2
Requires-Python: >=3.10
Requires-Dist: odoo-addon-delivery_carrier_account==18.0.*
Requires-Dist: odoo-addon-delivery_carrier_info==18.0.*
Requires-Dist: odoo-addon-delivery_carrier_shipping_label==18.0.*
Requires-Dist: odoo==18.0.*
Requires-Dist: roulier
Summary: Integration of multiple carriers
Home-page: https://github.com/OCA/delivery-carrier
License: AGPL-3
Author: Akretion,Odoo Community Association (OCA)
Author-email: support@odoo-community.org
Classifier: Programming Language :: Python
Classifier: Framework :: Odoo
Classifier: Framework :: Odoo :: 18.0
Classifier: License :: OSI Approved :: GNU Affero General Public License v3
